{"pools":[{"bonus_rolls":0.0,"entries":[{"children":[{"conditions":[{"condition":"minecraft:match_tool","predicate":{"enchantments":[{"enchantment":"minecraft:silk_touch","levels":{"min":1}}]}}],"functions":[{"function":"minecraft:copy_nbt","ops":[{"op":"replace","source":"Bees","target":"BlockEntityTag.Bees"}],"source":"block_entity"},{"block":"minecraft:bee_nest","function":"minecraft:copy_state","properties":["honey_level"]}],"name":"minecraft:bee_nest","type":"minecraft:item"},{"functions":[{"count":3.0,"function":"minecraft:set_count"},{"add":true,"conditions":[{"block":"minecraft:bee_nest","condition":"minecraft:block_state_property","properties":{"honey_level":"5"}}],"count":3.0,"function":"minecraft:set_count"},{"function":"minecraft:explosion_decay"}],"name":"minecraft:honeycomb","type":"minecraft:item"}],"type":"minecraft:alternatives"}],"rolls":1.0}],"random_sequence":"minecraft:blocks/bee_nest","type":"minecraft:block"}